slingshot/__init__.py
slingshot/cli/__init__.py
slingshot/cli/add.py
slingshot/cli/apply.py
slingshot/cli/apps.py
slingshot/cli/artifact.py
slingshot/cli/auth.py
slingshot/cli/code.py
slingshot/cli/config/__init__.py
slingshot/cli/config/py.typed
slingshot/cli/config/sentry_setup.py
slingshot/cli/config/slingshot_cli.py
slingshot/cli/deployment.py
slingshot/cli/dev.py
slingshot/cli/environment.py
slingshot/cli/logs.py
slingshot/cli/machine.py
slingshot/cli/main.py
slingshot/cli/project.py
slingshot/cli/py.typed
slingshot/cli/run.py
slingshot/cli/secret.py
slingshot/cli/session.py
slingshot/cli/shared/__init__.py
slingshot/cli/shared/code_sync.py
slingshot/cli/shared/formatting.py
slingshot/cli/shared/handle_interrupts.py
slingshot/cli/shared/prompt.py
slingshot/cli/shared/py.typed
slingshot/cli/shared/settings.py
slingshot/cli/shared/ssh.py
slingshot/cli/shared/utils.py
slingshot/cli/volume.py
slingshot/code/__init__.py
slingshot/code/annotation.py
slingshot/code/py.typed
slingshot/inference/__init__.py
slingshot/inference/inference_model.py
slingshot/schemas/__init__.py
slingshot/schemas/apps.py
slingshot/schemas/common.py
slingshot/schemas/components.py
slingshot/schemas/deployments.py
slingshot/schemas/environments.py
slingshot/schemas/mixins.py
slingshot/schemas/mounts.py
slingshot/schemas/project.py
slingshot/schemas/protocols.py
slingshot/schemas/py.typed
slingshot/schemas/runs.py
slingshot/schemas/slingshot-schema.config.json
slingshot/schemas/sources.py
slingshot/schemas/utils.py
slingshot/sdk/__init__.py
slingshot/sdk/apply.py
slingshot/sdk/apply_diff.py
slingshot/sdk/auth.py
slingshot/sdk/backend_schemas/__init__.py
slingshot/sdk/backend_schemas/generated/__init__.py
slingshot/sdk/backend_schemas/generated/py.typed
slingshot/sdk/backend_schemas/generated/schemas.py
slingshot/sdk/backend_schemas/schema_extras.py
slingshot/sdk/backend_schemas/schema_overrides.py
slingshot/sdk/config.py
slingshot/sdk/config_utils.py
slingshot/sdk/data_collector.py
slingshot_ai-0.0.28.dist-info/METADATA
slingshot_ai-0.0.28.dist-info/WHEEL
slingshot_ai-0.0.28.dist-info/entry_points.txt
slingshot_ai-0.0.28.dist-info/RECORD
